MANIFEST.in
local_build_sample.py
setup.cfg
setup.py
bitmagic.egg-info/PKG-INFO
bitmagic.egg-info/SOURCES.txt
bitmagic.egg-info/dependency_links.txt
bitmagic.egg-info/entry_points.txt
bitmagic.egg-info/not-zip-safe
bitmagic.egg-info/top_level.txt
bm/__init__.py
src/bm.cpp
src/include/bm.h
src/include/bmalgo.h
src/include/bmalgo_impl.h
src/include/bmalloc.h
src/include/bmblocks.h
src/include/bmconst.h
src/include/bmdbg.h
src/include/bmdef.h
src/include/bmfunc.h
src/include/bmfwd.h
src/include/bmgamma.h
src/include/bmrandom.h
src/include/bmserial.h
src/include/bmsse2.h
src/include/bmsse4.h
src/include/bmsse_util.h
src/include/bmtrans.h
src/include/bmundef.h
src/include/bmutil.h
src/include/bmvmin.h
src/include/encoding.h
tests/bm_test.py