Metadata-Version: 1.0
Name: bitmagic
Version: 0.1dev
Summary: Python wrapper for BitMagic
Home-page: UNKNOWN
Author: William Waites
Author-email: wwaites_at_gmail.com
License: BSD
Keywords: binary vector
Platform: UNKNOWN
